{
  "description": "智慧学堂微信小程序",
  "packOptions": {
    "ignore": [
      {
        "type": "file",
        "value": ".eslintrc.js"
      }
    ]
  },
  "setting": {
    "urlCheck": true,
    "es6": true,
    "enhance": true,
    "postcss": true,
    "preloadBackgroundData": false,
    "minified": true,
    "newFeature": false,
    "coverView": true,
    "nodeModules": true,
    "autoAudits": false,
    "showShadowRootInWxmlPanel": true,
    "scopeDataCheck": false,
    "uglifyFileName": false,
    "checkInvalidKey": true,
    "checkSiteMap": true,
    "uploadWithSourceMap": true,
    "compileHotReLoad": false,
    "lazyloadPlaceholderEnable": false,
    "preloadSitemap": false,
    "compileType": "miniprogram",
    "useMultiFrameRuntime": true,
    "useApiHook": true,
    "useApiHostProcess": true,
    "babelSetting": {
      "ignore": [],
      "disablePlugins": [],
      "outputPath": ""
    },
    "disableUseStrict": false,
    "minifyWXSS": true,
    "disableShowShadowRootInWxmlPanel": false,
    "minifyWXML": true,
    "showES6CompileOption": false,
    "minifyJS": true,
    "packNpmManually": true,
    "packNpmRelationList": [
      {
        "packageJsonPath": "./package.json",
        "miniprogramNpmDistDir": "./miniprogram_npm"
      }
    ],
    "lazyCodeLoading": "requiredComponents"
  },
  "libVersion": "2.14.4",
  "appid": "wx071081893fb8346b",
  "projectname": "智慧学堂",
  "debugOptions": {
    "hidedInDevtools": []
  },
  "scripts": {},
  "staticServerOptions": {
    "baseURL": "",
    "servePath": ""
  },
  "isGameTourist": false,
  "condition": {
    "search": {
      "list": []
    },
    "conversation": {
      "list": []
    },
    "game": {
      "list": []
    },
    "plugin": {
      "list": []
    },
    "gamePlugin": {
      "list": []
    },
    "miniprogram": {
      "list": []
    }
  },
  "cloudfunctionTemplateRoot": "cloudfunctionTemplate/",
  "cloudfunctionRoot": "cloudfunctions/"
}